{
  "lesson_id": "L9_divide_by_9",
  "title": "Divide by 9",
  "grade": "G3",
  "unit": "U7_division_facts_strategies",
  "ccss": [
    "3.OA.C.7"
  ],
  "go_math_ref": {
    "chapter": 7,
    "lesson": "7.9",
    "pages": "299-302"
  },
  "essential_question": "How can you divide by 9?",
  "key_vocabulary": [
    "divide",
    "nine",
    "quotient",
    "digit sum",
    "pattern"
  ],
  "strategies": [
    "Use ×9 facts in reverse.",
    "Check digit sum: digits of 9s multiples add to 9.",
    "Draw 9 equal groups."
  ],
  "pretest": [
    {
      "type": "mc",
      "choices": [
        "A) 1",
        "B) 2",
        "C) 3",
        "D) 4"
      ],
      "explanation": "18 ÷ 9 = 2.",
      "difficulty": 1,
      "id": "PT_01",
      "question": "18 ÷ 9 = ?",
      "correct_answer": "B",
      "feedback": {
        "correct": "Correct!",
        "incorrect": "18 ÷ 9 = 2."
      }
    },
    {
      "type": "mc",
      "choices": [
        "A) 3",
        "B) 4",
        "C) 5",
        "D) 6"
      ],
      "explanation": "36 ÷ 9 = 4.",
      "difficulty": 1,
      "id": "PT_02",
      "question": "36 ÷ 9 = ?",
      "correct_answer": "B",
      "feedback": {
        "correct": "Correct!",
        "incorrect": "36 ÷ 9 = 4."
      }
    },
    {
      "type": "mc",
      "choices": [
        "A) 4",
        "B) 5",
        "C) 6",
        "D) 7"
      ],
      "explanation": "45 ÷ 9 = 5.",
      "difficulty": 1,
      "id": "PT_03",
      "question": "45 ÷ 9 = ?",
      "correct_answer": "B",
      "feedback": {
        "correct": "Correct!",
        "incorrect": "45 ÷ 9 = 5."
      }
    },
    {
      "type": "mc",
      "choices": [
        "A) 6",
        "B) 7",
        "C) 8",
        "D) 9"
      ],
      "explanation": "63 ÷ 9 = 7.",
      "difficulty": 1,
      "id": "PT_04",
      "question": "63 ÷ 9 = ?",
      "correct_answer": "B",
      "feedback": {
        "correct": "Correct!",
        "incorrect": "63 ÷ 9 = 7."
      }
    },
    {
      "type": "mc",
      "choices": [
        "A) 7",
        "B) 8",
        "C) 9",
        "D) 10"
      ],
      "explanation": "81 ÷ 9 = 9.",
      "difficulty": 1,
      "id": "PT_05",
      "question": "81 beads are strung into 9 equal necklaces. How many beads each?",
      "correct_answer": "C",
      "feedback": {
        "correct": "Correct!",
        "incorrect": "81 ÷ 9 = 9."
      }
    }
  ],
  "learn": [
    {
      "type": "concept_card",
      "title": "Sharing Into 9 Equal Groups",
      "content": "When you divide by 9, you share a total equally among 9 groups. Example: 54 counters shared into 9 groups → each group gets 6. So 54 ÷ 9 = 6.",
      "id": "LN_01",
      "cpa_phase": "concrete",
      "visual_type": "manipulative",
      "visual_data": {
        "tool": "counter_groups",
        "config": {
          "total": 54,
          "groups": 9,
          "per_group": 6
        }
      }
    },
    {
      "type": "concept_card",
      "title": "Array: 9 Rows",
      "content": "A 9×8 array has 72 tiles arranged in 9 rows of 8. Reading it as division: 72 tiles in 9 rows means 72 ÷ 9 = 8 tiles per row. The ×9 fact 9×8=72 gives the ÷9 fact 72÷9=8.",
      "id": "LN_02",
      "cpa_phase": "concrete",
      "visual_type": "manipulative",
      "visual_data": {
        "tool": "array_grid",
        "config": {
          "rows": 9,
          "cols": 8
        }
      }
    },
    {
      "type": "concept_card",
      "title": "Digit-Sum Trick for Multiples of 9",
      "content": "Every multiple of 9 has digits that add up to 9. This helps you check ÷9 answers:\n9×1=9 → digits: 9 ✓\n9×2=18 → 1+8=9 ✓\n9×3=27 → 2+7=9 ✓\n9×4=36 → 3+6=9 ✓\n9×5=45 → 4+5=9 ✓\n9×6=54 → 5+4=9 ✓\n9×7=63 → 6+3=9 ✓\n9×8=72 → 7+2=9 ✓\n9×9=81 → 8+1=9 ✓",
      "id": "LN_03",
      "cpa_phase": "pictorial",
      "visual_type": "diagram",
      "visual_data": {
        "tool": "digit_sum_table",
        "config": {
          "divisor": 9,
          "range": [
            1,
            9
          ]
        }
      }
    },
    {
      "type": "concept_card",
      "title": "Number Line: Backward Jumps of 9",
      "content": "To find 81 ÷ 9, start at 81 on a number line and hop backward by 9 each time: 81 → 72 → 63 → 54 → 45 → 36 → 27 → 18 → 9 → 0. Count the hops: 9 hops. So 81 ÷ 9 = 9.",
      "id": "LN_04",
      "cpa_phase": "pictorial",
      "visual_type": "number_line",
      "visual_data": {
        "tool": "number_line",
        "config": {
          "start": 81,
          "end": 0,
          "jump": -9,
          "label": "81 ÷ 9 = 9 hops"
        }
      }
    },
    {
      "type": "concept_card",
      "title": "The ÷9 Pattern: Reverse the ×9 Fact",
      "content": "Every ×9 fact gives you a ÷9 fact:\n9×1=9 → 9÷9=1\n9×2=18 → 18÷9=2\n9×3=27 → 27÷9=3\n9×4=36 → 36÷9=4\n9×5=45 → 45÷9=5\n9×6=54 → 54÷9=6\n9×7=63 → 63÷9=7\n9×8=72 → 72÷9=8\n9×9=81 → 81÷9=9\n9×10=90 → 90÷9=10\nStrategy: think '9 × ? = dividend' to find the quotient.",
      "id": "LN_05",
      "cpa_phase": "abstract",
      "visual_type": "table",
      "visual_data": {
        "tool": "fact_table",
        "config": {
          "divisor": 9,
          "range": [
            1,
            10
          ]
        }
      }
    }
  ],
  "try": [
    {
      "type": "mc",
      "problem_id": "TRY_01",
      "choices": [
        "A) 0",
        "B) 1",
        "C) 9",
        "D) 18"
      ],
      "explanation": "9 ÷ 9 = 1. Any number divided by itself is 1.",
      "difficulty": 1,
      "id": "TRY_01",
      "hints": [
        "Use the 9× fact: 9 × ? = 9. Only 9 × 1 = 9.",
        "How many groups of 9 fit inside 9? Just one."
      ],
      "feedback": {
        "correct": "Right! 9 ÷ 9 = 1.",
        "incorrect": "9 ÷ 9 means how many groups of 9 in 9. Just one: 9 ÷ 9 = 1."
      },
      "solution_steps": [
        "9 × 1 = 9",
        "So 9 ÷ 9 = 1"
      ],
      "question": "9 ÷ 9 = ?",
      "correct_answer": "B"
    },
    {
      "type": "mc",
      "problem_id": "TRY_02",
      "choices": [
        "A) 2",
        "B) 3",
        "C) 4",
        "D) 5"
      ],
      "explanation": "27 ÷ 9 = 3. Think: 9 × 3 = 27.",
      "difficulty": 1,
      "id": "TRY_02",
      "hints": [
        "Use the 9× fact: 9 × ? = 27. Think: 27 ÷ 9 = ?",
        "Digit-sum check: the quotient × 9 should have digits that add to 9. Try 3: 3×9=27, 2+7=9 ✓"
      ],
      "feedback": {
        "correct": "Yes! 9 × 3 = 27, so each group has 3 players.",
        "incorrect": "9 × 3 = 27, so 27 ÷ 9 = 3 players per group."
      },
      "solution_steps": [
        "9 × 3 = 27",
        "So 27 ÷ 9 = 3"
      ],
      "question": "A team has 27 players split into 9 equal groups. How many players per group?",
      "correct_answer": "B"
    },
    {
      "type": "input",
      "problem_id": "TRY_03",
      "explanation": "18 ÷ 9 = 2. Think: 9 × 2 = 18.",
      "difficulty": 1,
      "id": "TRY_03",
      "hints": [
        "Use the 9× fact: 9 × ? = 18. Think: 18 ÷ 9 = ?",
        "Digit-sum check: 1+8=9 ✓ so 18 is a multiple of 9. Count: 9,18 — 2 counts."
      ],
      "feedback": {
        "correct": "Correct! 9 × 2 = 18, so 18 ÷ 9 = 2.",
        "incorrect": "9 × 2 = 18, so 18 ÷ 9 = 2."
      },
      "solution_steps": [
        "9 × 2 = 18",
        "So 18 ÷ 9 = 2"
      ],
      "question": "18 ÷ 9 = ___",
      "correct_answer": "2"
    },
    {
      "type": "input",
      "problem_id": "TRY_04",
      "explanation": "63 ÷ 9 = 7. Think: 9 × 7 = 63.",
      "difficulty": 1,
      "id": "TRY_04",
      "hints": [
        "Use the 9× fact: 9 × ? = 63. Think: 63 ÷ 9 = ?",
        "Digit-sum check: 6+3=9 ✓ so 63 is a multiple of 9. Skip count by 9s to 63 — 7 counts."
      ],
      "feedback": {
        "correct": "Great! 9 × 7 = 63, so 63 ÷ 9 = 7.",
        "incorrect": "Count by 9s to 63: 9,18,27,36,45,54,63 — 7 counts. So 63 ÷ 9 = 7."
      },
      "solution_steps": [
        "9 × 7 = 63",
        "So 63 ÷ 9 = 7"
      ],
      "question": "63 ÷ 9 = ___",
      "correct_answer": "7"
    },
    {
      "type": "mc",
      "problem_id": "TRY_05",
      "choices": [
        "A) 8",
        "B) 9",
        "C) 10",
        "D) 11"
      ],
      "explanation": "90 ÷ 9 = 10. Think: 9 × 10 = 90.",
      "difficulty": 1,
      "id": "TRY_05",
      "hints": [
        "Use the 9× fact: 9 × ? = 90. Think: 90 ÷ 9 = ?",
        "Digit-sum check: 9+0=9 ✓ so 90 is a multiple of 9. Count by 9s to 90 — 10 counts."
      ],
      "feedback": {
        "correct": "Yes! 9 × 10 = 90, so each shelf has 10 books.",
        "incorrect": "9 × 10 = 90, so 90 ÷ 9 = 10 books per shelf."
      },
      "solution_steps": [
        "9 × 10 = 90",
        "So 90 ÷ 9 = 10 books per shelf"
      ],
      "question": "A bookstore arranges 90 books equally on 9 shelves. How many books per shelf?",
      "correct_answer": "C"
    }
  ],
  "practice_r1": [
    {
      "type": "mc",
      "problem_id": "R1_01",
      "choices": [
        "A) 0",
        "B) 1",
        "C) 9",
        "D) 18"
      ],
      "explanation": "9 ÷ 9 = 1.",
      "difficulty": 1,
      "id": "R1_01",
      "hints": [
        "Use the 9× fact: 9 × ? = 9. Only 9 × 1 = 9.",
        "How many groups of 9 fit inside 9? Just one."
      ],
      "feedback": {
        "correct": "Right! 9 ÷ 9 = 1.",
        "incorrect": "Any number divided by itself is 1. So 9 ÷ 9 = 1."
      },
      "question": "9 ÷ 9 = ?",
      "correct_answer": "B"
    },
    {
      "type": "mc",
      "problem_id": "R1_02",
      "choices": [
        "A) 2",
        "B) 3",
        "C) 4",
        "D) 5"
      ],
      "explanation": "27 ÷ 9 = 3. Think: 9 × 3 = 27.",
      "difficulty": 1,
      "id": "R1_02",
      "hints": [
        "Use the 9× fact: 9 × ? = 27. Think: 27 ÷ 9 = ?",
        "Skip count by 9s: 9, 18, 27. How many counts?"
      ],
      "feedback": {
        "correct": "Correct! 9 × 3 = 27, so 27 ÷ 9 = 3.",
        "incorrect": "Count by 9s to 27: 9(1), 18(2), 27(3). So 27 ÷ 9 = 3."
      },
      "question": "27 ÷ 9 = ?",
      "correct_answer": "B"
    },
    {
      "type": "mc",
      "problem_id": "R1_03",
      "choices": [
        "A) 5",
        "B) 6",
        "C) 7",
        "D) 8"
      ],
      "explanation": "54 ÷ 9 = 6. Think: 9 × 6 = 54.",
      "difficulty": 1,
      "id": "R1_03",
      "hints": [
        "Use the 9× fact: 9 × ? = 54. Think: 54 ÷ 9 = ?",
        "Digit-sum check: 5+4=9 ✓. Skip count by 9s to 54 — 6 counts."
      ],
      "feedback": {
        "correct": "Yes! 9 × 6 = 54, so 54 ÷ 9 = 6.",
        "incorrect": "Count by 9s to 54 — that takes 6 counts. So 54 ÷ 9 = 6."
      },
      "question": "54 ÷ 9 = ?",
      "correct_answer": "B"
    },
    {
      "type": "mc",
      "problem_id": "R1_04",
      "choices": [
        "A) 7",
        "B) 8",
        "C) 9",
        "D) 10"
      ],
      "explanation": "72 ÷ 9 = 8. Think: 9 × 8 = 72.",
      "difficulty": 1,
      "id": "R1_04",
      "hints": [
        "Use the 9× fact: 9 × ? = 72. Think: 72 ÷ 9 = ?",
        "Digit-sum check: 7+2=9 ✓. Skip count by 9s to 72 — 8 counts."
      ],
      "feedback": {
        "correct": "Excellent! 9 × 8 = 72, so 72 ÷ 9 = 8.",
        "incorrect": "Count by 9s to 72 — that takes 8 counts. So 72 ÷ 9 = 8."
      },
      "question": "72 ÷ 9 = ?",
      "correct_answer": "B"
    },
    {
      "type": "mc",
      "problem_id": "R1_05",
      "choices": [
        "A) 3",
        "B) 4",
        "C) 5",
        "D) 6"
      ],
      "explanation": "36 ÷ 9 = 4 boxes. Think: 9 × 4 = 36.",
      "difficulty": 1,
      "id": "R1_05",
      "hints": [
        "Use the 9× fact: 9 × ? = 36. Think: 36 ÷ 9 = ?",
        "Digit-sum check: 3+6=9 ✓. Count by 9s to 36: 9,18,27,36 — 4 counts."
      ],
      "feedback": {
        "correct": "Right! 9 × 4 = 36, so 36 markers fill 4 boxes.",
        "incorrect": "Count by 9s to 36 — that takes 4 counts. So 36 ÷ 9 = 4 boxes."
      },
      "question": "A box holds 9 markers. How many boxes do 36 markers fill?",
      "correct_answer": "B"
    },
    {
      "type": "mc",
      "problem_id": "R1_06",
      "choices": [
        "A) 4",
        "B) 5",
        "C) 6",
        "D) 7"
      ],
      "explanation": "45 ÷ 9 = 5 flags. Think: 9 × 5 = 45.",
      "difficulty": 1,
      "id": "R1_06",
      "hints": [
        "Use the 9× fact: 9 × ? = 45. Think: 45 ÷ 9 = ?",
        "Digit-sum check: 4+5=9 ✓. Count by 9s to 45: 9,18,27,36,45 — 5 counts."
      ],
      "feedback": {
        "correct": "Right! 9 × 5 = 45, so there are 5 flags.",
        "incorrect": "Count by 9s to 45 — that takes 5 counts. So 45 ÷ 9 = 5 flags."
      },
      "question": "A flag has 9 stripes. If there are 45 stripes in total, how many flags are there?",
      "correct_answer": "B"
    },
    {
      "type": "mc",
      "problem_id": "R1_07",
      "choices": [
        "A) 6",
        "B) 7",
        "C) 8",
        "D) 9"
      ],
      "explanation": "63 ÷ 9 = 7. Division reverses multiplication.",
      "difficulty": 1,
      "id": "R1_07",
      "hints": [
        "Multiplication and division are opposites: if 9 × 7 = 63, reverse it.",
        "9 × 7 = 63 means 63 shared into 9 groups gives 7 each. So 63 ÷ 9 = ?"
      ],
      "feedback": {
        "correct": "Exactly! 9 × 7 = 63 tells you 63 ÷ 9 = 7.",
        "incorrect": "Division reverses multiplication. 9 × 7 = 63, so 63 ÷ 9 = 7."
      },
      "question": "If 9 × 7 = 63, then 63 ÷ 9 = ?",
      "correct_answer": "B"
    },
    {
      "type": "input",
      "problem_id": "R1_08",
      "explanation": "81 ÷ 9 = 9. Think: 9 × 9 = 81.",
      "difficulty": 1,
      "id": "R1_08",
      "hints": [
        "Use the 9× fact: 9 × ? = 81. Think: 81 ÷ 9 = ?",
        "Digit-sum check: 8+1=9 ✓. Count by 9s to 81 — 9 counts."
      ],
      "feedback": {
        "correct": "Yes! 9 × 9 = 81, so 81 ÷ 9 = 9.",
        "incorrect": "Count by 9s to 81 — that takes 9 counts. So 81 ÷ 9 = 9."
      },
      "question": "81 ÷ 9 = ___",
      "correct_answer": "9"
    },
    {
      "type": "input",
      "problem_id": "R1_09",
      "explanation": "90 ÷ 9 = 10. Think: 9 × 10 = 90.",
      "difficulty": 1,
      "id": "R1_09",
      "hints": [
        "Use the 9× fact: 9 × ? = 90. Think: 90 ÷ 9 = ?",
        "Digit-sum check: 9+0=9 ✓. Ten groups of 9 make 90."
      ],
      "feedback": {
        "correct": "Perfect! 9 × 10 = 90, so 90 ÷ 9 = 10.",
        "incorrect": "9 × 10 = 90, so 90 ÷ 9 = 10."
      },
      "question": "90 ÷ 9 = ___",
      "correct_answer": "10"
    },
    {
      "type": "input",
      "problem_id": "R1_10",
      "explanation": "72 ÷ 9 = 8. Think: 9 × 8 = 72.",
      "difficulty": 1,
      "id": "R1_10",
      "hints": [
        "Use the 9× fact: 9 × ? = 72. Think: 72 ÷ 9 = ?",
        "Digit-sum check: 7+2=9 ✓. Count by 9s to 72 — 8 counts."
      ],
      "feedback": {
        "correct": "Great! 9 × 8 = 72, so 72 ÷ 9 = 8.",
        "incorrect": "Count by 9s to 72 — that takes 8 counts. So 72 ÷ 9 = 8."
      },
      "question": "72 ÷ 9 = ___",
      "correct_answer": "8"
    }
  ],
  "practice_r2": [
    {
      "type": "mc",
      "problem_id": "R2_01",
      "choices": [
        "A) 6",
        "B) 8",
        "C) 9",
        "D) 10"
      ],
      "explanation": "3 + 6 = 9. This confirms 36 is a multiple of 9.",
      "difficulty": 2,
      "id": "R2_01",
      "hints": [
        "Add the digits of 36: 3 + 6 = ?",
        "Every multiple of 9 has digits that sum to 9."
      ],
      "feedback": {
        "correct": "Correct! 3+6=9, confirming 36 is a multiple of 9.",
        "incorrect": "Add the digits of 36: 3+6=9. Every multiple of 9 has a digit sum of 9."
      },
      "question": "Use the digit-sum test: 36 ÷ 9 = 4. What do the digits of 36 add up to?",
      "correct_answer": "C"
    },
    {
      "type": "mc",
      "problem_id": "R2_02",
      "choices": [
        "A) 9 × 6 = 54",
        "B) 9 × 7 = 63",
        "C) 9 × 8 = 72",
        "D) 9 × 9 = 81"
      ],
      "explanation": "9 × 8 = 72, so 72 ÷ 9 = 8.",
      "difficulty": 2,
      "id": "R2_02",
      "hints": [
        "To divide 72 by 9, think: which 9× fact has 72 as the product?",
        "Check each: 9×6=54, 9×7=63, 9×8=72 ← that's it!"
      ],
      "feedback": {
        "correct": "Right! 9 × 8 = 72, so 72 ÷ 9 = 8.",
        "incorrect": "Find the 9× fact where the product is 72. 9 × 8 = 72, so 72 ÷ 9 = 8."
      },
      "question": "Which multiplication fact helps you solve 72 ÷ 9?",
      "correct_answer": "C"
    },
    {
      "type": "mc",
      "problem_id": "R2_03",
      "choices": [
        "A) 45",
        "B) 54",
        "C) 63",
        "D) 72"
      ],
      "explanation": "9 × 6 = 54, so 54 ÷ 9 = 6.",
      "difficulty": 2,
      "id": "R2_03",
      "hints": [
        "The quotient is 6 and the divisor is 9. Multiply back: 9 × 6 = ?",
        "Think: ? = 9 × 6 = 54. Check: 54 ÷ 9 = 6 ✓ (5+4=9 ✓)"
      ],
      "feedback": {
        "correct": "Correct! 9 × 6 = 54, so the missing number is 54.",
        "incorrect": "Work backwards: ? ÷ 9 = 6 means ? = 9 × 6 = 54."
      },
      "question": "? ÷ 9 = 6. What is the missing number?",
      "correct_answer": "B"
    },
    {
      "type": "mc",
      "problem_id": "R2_04",
      "choices": [
        "A) 18 ÷ 9",
        "B) 45 ÷ 9",
        "C) 63 ÷ 9",
        "D) 81 ÷ 9"
      ],
      "explanation": "18÷9=2, 45÷9=5, 63÷9=7, 81÷9=9. Greatest quotient is 9.",
      "difficulty": 2,
      "id": "R2_04",
      "hints": [
        "Solve each: 18÷9=?, 45÷9=?, 63÷9=?, 81÷9=?",
        "The largest dividend gives the largest quotient when dividing by 9."
      ],
      "feedback": {
        "correct": "Yes! 81÷9=9 is the greatest quotient.",
        "incorrect": "18÷9=2, 45÷9=5, 63÷9=7, 81÷9=9. The greatest is 9, from 81÷9."
      },
      "question": "Which division has the GREATEST quotient?",
      "correct_answer": "D"
    },
    {
      "type": "input",
      "problem_id": "R2_05",
      "explanation": "9 ÷ 9 = 1. Any number divided by itself is 1.",
      "difficulty": 2,
      "id": "R2_05",
      "hints": [
        "Use the 9× fact: 9 × ? = 9. Only 9 × 1 = 9.",
        "How many groups of 9 fit inside 9? Just one."
      ],
      "feedback": {
        "correct": "Correct! 9 ÷ 9 = 1.",
        "incorrect": "9 ÷ 9 means how many groups of 9 in 9. Just one: 9 ÷ 9 = 1."
      },
      "question": "9 ÷ 9 = ___",
      "correct_answer": "1"
    },
    {
      "type": "input",
      "problem_id": "R2_06",
      "explanation": "9 × 8 = 72, so 72 ÷ 9 = 8.",
      "difficulty": 2,
      "id": "R2_06",
      "hints": [
        "The quotient is 8 and the divisor is 9. Multiply back: 9 × 8 = ?",
        "Think: ? = 9 × 8 = 72. Check: 72 ÷ 9 = 8 ✓ (7+2=9 ✓)"
      ],
      "feedback": {
        "correct": "Right! 9 × 8 = 72, so the missing number is 72.",
        "incorrect": "Work backwards: ? ÷ 9 = 8 means ? = 9 × 8 = 72."
      },
      "question": "? ÷ 9 = 8. What is the missing dividend?",
      "correct_answer": "72"
    },
    {
      "type": "mc",
      "problem_id": "R2_07",
      "choices": [
        "A) 18 ÷ 9 = 2",
        "B) 45 ÷ 9 = 5",
        "C) 63 ÷ 9 = 8",
        "D) 81 ÷ 9 = 9"
      ],
      "explanation": "63 ÷ 9 = 7, not 8. All other facts are correct.",
      "difficulty": 2,
      "id": "R2_07",
      "hints": [
        "Check each fact: does it match a 9× multiplication fact?",
        "For 63 ÷ 9: digit-sum check 6+3=9 ✓. Count by 9s to 63 — that's 7 counts, not 8."
      ],
      "feedback": {
        "correct": "Correct! 63 ÷ 9 = 7, not 8. Count by 9s to 63 — 7 counts.",
        "incorrect": "Check 63 ÷ 9: 9×7=63, so 63÷9=7. The claim of 8 is wrong."
      },
      "question": "Which is NOT a correct ÷9 fact?",
      "correct_answer": "C"
    },
    {
      "type": "input",
      "problem_id": "R2_08",
      "explanation": "45 ÷ 9 = 5. Think: 9 × 5 = 45.",
      "difficulty": 2,
      "id": "R2_08",
      "hints": [
        "Use the 9× fact: 9 × ? = 45. Think: 45 ÷ 9 = ?",
        "Digit-sum check: 4+5=9 ✓. Count by 9s to 45: 9,18,27,36,45 — 5 counts."
      ],
      "feedback": {
        "correct": "Yes! 9 × 5 = 45, so 45 ÷ 9 = 5.",
        "incorrect": "Count by 9s to 45 — that takes 5 counts. So 45 ÷ 9 = 5."
      },
      "question": "45 ÷ 9 = ___",
      "correct_answer": "5"
    },
    {
      "type": "input",
      "problem_id": "R2_09",
      "explanation": "54 ÷ 9 = 6. Think: 9 × 6 = 54.",
      "difficulty": 2,
      "id": "R2_09",
      "hints": [
        "Use the 9× fact: 9 × ? = 54. Think: 54 ÷ 9 = ?",
        "Digit-sum check: 5+4=9 ✓. Count by 9s to 54 — 6 counts."
      ],
      "feedback": {
        "correct": "Great! 9 × 6 = 54, so 54 ÷ 9 = 6.",
        "incorrect": "Count by 9s to 54 — that takes 6 counts. So 54 ÷ 9 = 6."
      },
      "question": "54 ÷ 9 = ___",
      "correct_answer": "6"
    },
    {
      "type": "mc",
      "problem_id": "R2_10",
      "choices": [
        "A) 4",
        "B) 5",
        "C) 6",
        "D) 7"
      ],
      "explanation": "18÷9=2, 27÷9=3. 2+3=5.",
      "difficulty": 2,
      "id": "R2_10",
      "hints": [
        "Solve inside the parentheses first: 18÷9=? and 27÷9=?",
        "After dividing: 18÷9=2, 27÷9=3. Now add those two quotients."
      ],
      "feedback": {
        "correct": "Yes! 18÷9=2, 27÷9=3, and 2+3=5.",
        "incorrect": "Step 1: 18÷9=2. Step 2: 27÷9=3. Step 3: 2+3=5."
      },
      "question": "(18 ÷ 9) + (27 ÷ 9) = ?",
      "correct_answer": "B"
    }
  ],
  "practice_r3": [
    {
      "type": "mc",
      "problem_id": "R3_01",
      "choices": [
        "A) 16",
        "B) 18",
        "C) 20",
        "D) 24"
      ],
      "explanation": "81 ÷ 9 = 9 students per group. 9 groups × 2 posters = 18 posters.",
      "difficulty": 3,
      "id": "R3_01",
      "hints": [
        "Step 1: how many students per group? 81 ÷ 9 = ?",
        "Step 2: multiply number of groups × 2 posters per group."
      ],
      "feedback": {
        "correct": "Right! 81÷9=9 per group. 9 groups × 2 = 18 posters.",
        "incorrect": "81÷9=9 per group. There are 9 groups, each making 2 posters: 9×2=18 total."
      },
      "question": "A class of 81 students is split into 9 equal groups. Each group makes 2 posters. How many posters in total?",
      "correct_answer": "B"
    },
    {
      "type": "mc",
      "problem_id": "R3_02",
      "choices": [
        "A) 6",
        "B) 7",
        "C) 8",
        "D) 9"
      ],
      "explanation": "Mystery number = 9 × 7 = 63. Digit sum: 6 + 3 = 9.",
      "difficulty": 3,
      "id": "R3_02",
      "hints": [
        "Step 1: find the mystery number — if ? ÷ 9 = 7, then ? = 9 × 7 = ?",
        "Step 2: add the digits of that number. Every multiple of 9 has a digit sum of 9!"
      ],
      "feedback": {
        "correct": "Correct! 9×7=63 is the mystery number, and 6+3=9.",
        "incorrect": "? ÷ 9 = 7 → ? = 9×7 = 63. Digit sum: 6+3=9."
      },
      "question": "A mystery number ÷ 9 = 7. What do the digits of the mystery number add up to?",
      "correct_answer": "D"
    },
    {
      "type": "mc",
      "problem_id": "R3_03",
      "choices": [
        "A) 7",
        "B) 8",
        "C) 9",
        "D) 10"
      ],
      "explanation": "54 + 27 = 81 total stickers. 81 ÷ 9 = 9 pages.",
      "difficulty": 3,
      "id": "R3_03",
      "hints": [
        "Step 1: add all stickers together: 54 + 27 = ?",
        "Step 2: divide total stickers by 9 (stickers per page)."
      ],
      "feedback": {
        "correct": "Yes! 54+27=81 stickers. 81÷9=9 pages total.",
        "incorrect": "54+27=81 total stickers. 81÷9=9 pages."
      },
      "question": "Tim has 54 stickers. He puts 9 on each page. Then he gets 27 more stickers and fills more pages. How many pages total does he fill?",
      "correct_answer": "C"
    },
    {
      "type": "mc",
      "problem_id": "R3_04",
      "choices": [
        "A) 40",
        "B) 43",
        "C) 45",
        "D) 48"
      ],
      "explanation": "81 ÷ 9 = 9 per bag. 9 − 4 = 5 bags remain. 5 × 9 = 45 marbles.",
      "difficulty": 3,
      "id": "R3_04",
      "hints": [
        "Step 1: find marbles per bag: 81 ÷ 9 = ?",
        "Step 2: 4 bags spill, so 9−4=5 bags remain. Multiply bags × marbles per bag."
      ],
      "feedback": {
        "correct": "Right! 81÷9=9 per bag. 5 bags remain. 5×9=45 marbles.",
        "incorrect": "81÷9=9 per bag. 9−4=5 bags remain. 5×9=45 marbles remain."
      },
      "question": "81 marbles are shared equally into 9 bags. Then 4 bags fall and spill. How many marbles remain in the bags?",
      "correct_answer": "C"
    },
    {
      "type": "input",
      "problem_id": "R3_05",
      "explanation": "9 × 9 = 81, so 81 ÷ 9 = 9.",
      "difficulty": 3,
      "id": "R3_05",
      "hints": [
        "The quotient is 9 and the divisor is 9. Multiply back: 9 × 9 = ?",
        "Think: ? = 9 × 9 = 81. Check: 81 ÷ 9 = 9 ✓ (8+1=9 ✓)"
      ],
      "feedback": {
        "correct": "Correct! 9 × 9 = 81, so the missing number is 81.",
        "incorrect": "Work backwards: ? ÷ 9 = 9 means ? = 9 × 9 = 81."
      },
      "question": "? ÷ 9 = 9. What is the missing dividend?",
      "correct_answer": "81"
    }
  ],
  "concept": "divide_by_9"
}
